{
  "type": "work",
  "uid": "hind-al-oud---immersive-pop-up",
  "lang": "en-us",
  "data": {
    "title": [
      {
        "type": "heading1",
        "text": "Hind Al Oud Pop-Up Store",
        "spans": []
      }
    ],
    "category": "immersive-environments-pop-ups",
    "client": "Hind Al Oud",
    "year": "2023",
    "location": "Galleria Mall, Abu Dhabi, UAE",
    "intro": [
      {
        "type": "paragraph",
        "text": "Immersive Pop-Up Store",
        "spans": []
      }
    ],
    "main_image": {
      "origin": {
        "url": "https://cdn.prod.website-files.com/68b1b40ff8f7a47bdc773ba5/68b31dd15a98c1de8d3f530b_16.png"
      },
      "url": "https://cdn.prod.website-files.com/68b1b40ff8f7a47bdc773ba5/68b31dd15a98c1de8d3f530b_16.png"
    },
    "preview_image": {
      "origin": {
        "url": "https://cdn.prod.website-files.com/68b1b40ff8f7a47bdc773ba5/68b31dd15a98c1de8d3f530b_16.png"
      },
      "url": "https://cdn.prod.website-files.com/68b1b40ff8f7a47bdc773ba5/68b31dd15a98c1de8d3f530b_16.png"
    },
    "slices": [
      {
        "slice_type": "content_block",
        "slice_label": null,
        "variation": "default",
        "primary": {
          "content": [
            {
              "type": "heading2",
              "text": "Design Concept",
              "spans": []
            },
            {
              "type": "paragraph",
              "text": "This immersive pop-up was designed as a luxury pavilion in the heart of Galleria Mall, combining bold architecture with sensorial storytelling to create a memorable retail destination.",
              "spans": []
            }
          ]
        },
        "items": []
      },
      {
        "slice_type": "image_gallery",
        "slice_label": null,
        "variation": "default",
        "primary": {},
        "items": [
          {
            "image": {
              "origin": {
                "url": "https://cdn.prod.website-files.com/68b1b40ff8f7a47bdc773ba5/68b31dd15a98c1de8d3f530b_16.png"
              },
              "url": "https://cdn.prod.website-files.com/68b1b40ff8f7a47bdc773ba5/68b31dd15a98c1de8d3f530b_16.png"
            },
            "caption": ""
          },
          {
            "image": {
              "origin": {
                "url": "https://cdn.prod.website-files.com/68b1b40ff8f7a47bdc773ba5/68b31dd158c2ba948b634f73_17.png"
              },
              "url": "https://cdn.prod.website-files.com/68b1b40ff8f7a47bdc773ba5/68b31dd158c2ba948b634f73_17.png"
            },
            "caption": ""
          },
          {
            "image": {
              "origin": {
                "url": "https://cdn.prod.website-files.com/68b1b40ff8f7a47bdc773ba5/68b31e55cfdd1b67049afb07_Captureww.JPG"
              },
              "url": "https://cdn.prod.website-files.com/68b1b40ff8f7a47bdc773ba5/68b31e55cfdd1b67049afb07_Captureww.JPG"
            },
            "caption": ""
          },
          {
            "image": {
              "origin": {
                "url": "https://cdn.prod.website-files.com/68b1b40ff8f7a47bdc773ba5/68b31dd1bab532707805fb89_14.png"
              },
              "url": "https://cdn.prod.website-files.com/68b1b40ff8f7a47bdc773ba5/68b31dd1bab532707805fb89_14.png"
            },
            "caption": ""
          },
          {
            "image": {
              "origin": {
                "url": "https://cdn.prod.website-files.com/68b1b40ff8f7a47bdc773ba5/68b3169695d8af8b0e6f3b30_3.png"
              },
              "url": "https://cdn.prod.website-files.com/68b1b40ff8f7a47bdc773ba5/68b3169695d8af8b0e6f3b30_3.png"
            },
            "caption": ""
          },
          {
            "image": {
              "origin": {
                "url": "https://cdn.prod.website-files.com/68b1b40ff8f7a47bdc773ba5/68b3168c5f8a5cce19c37ecc_11.png"
              },
              "url": "https://cdn.prod.website-files.com/68b1b40ff8f7a47bdc773ba5/68b3168c5f8a5cce19c37ecc_11.png"
            },
            "caption": ""
          },
          {
            "image": {
              "origin": {
                "url": "https://cdn.prod.website-files.com/68b1b40ff8f7a47bdc773ba5/68b316923c940a53d30406e2_4.png"
              },
              "url": "https://cdn.prod.website-files.com/68b1b40ff8f7a47bdc773ba5/68b316923c940a53d30406e2_4.png"
            },
            "caption": ""
          },
          {
            "image": {
              "origin": {
                "url": "https://cdn.prod.website-files.com/68b1b40ff8f7a47bdc773ba5/68b31691e38646b7c773f7d4_7.png"
              },
              "url": "https://cdn.prod.website-files.com/68b1b40ff8f7a47bdc773ba5/68b31691e38646b7c773f7d4_7.png"
            },
            "caption": ""
          },
          {
            "image": {
              "origin": {
                "url": "https://cdn.prod.website-files.com/68b1b40ff8f7a47bdc773ba5/68b3169428aa2dc316bfd797_5.png"
              },
              "url": "https://cdn.prod.website-files.com/68b1b40ff8f7a47bdc773ba5/68b3169428aa2dc316bfd797_5.png"
            },
            "caption": ""
          },
          {
            "image": {
              "origin": {
                "url": "https://cdn.prod.website-files.com/68b1b40ff8f7a47bdc773ba5/68b31692b2f93665e601617e_6.png"
              },
              "url": "https://cdn.prod.website-files.com/68b1b40ff8f7a47bdc773ba5/68b31692b2f93665e601617e_6.png"
            },
            "caption": ""
          },
          {
            "image": {
              "origin": {
                "url": "https://cdn.prod.website-files.com/68b1b40ff8f7a47bdc773ba5/68b316912245f238d5f36d37_8.png"
              },
              "url": "https://cdn.prod.website-files.com/68b1b40ff8f7a47bdc773ba5/68b316912245f238d5f36d37_8.png"
            },
            "caption": ""
          },
          {
            "image": {
              "origin": {
                "url": "https://cdn.prod.website-files.com/68b1b40ff8f7a47bdc773ba5/68b3168f9810e6cd45bcc23b_9.png"
              },
              "url": "https://cdn.prod.website-files.com/68b1b40ff8f7a47bdc773ba5/68b3168f9810e6cd45bcc23b_9.png"
            },
            "caption": ""
          },
          {
            "image": {
              "origin": {
                "url": "https://cdn.prod.website-files.com/68b1b40ff8f7a47bdc773ba5/68b3168edc6a6e119cd88504_12.png"
              },
              "url": "https://cdn.prod.website-files.com/68b1b40ff8f7a47bdc773ba5/68b3168edc6a6e119cd88504_12.png"
            },
            "caption": ""
          },
          {
            "image": {
              "origin": {
                "url": "https://cdn.prod.website-files.com/68b1b40ff8f7a47bdc773ba5/68b31694a8ef92db17dc86f2_1.png"
              },
              "url": "https://cdn.prod.website-files.com/68b1b40ff8f7a47bdc773ba5/68b31694a8ef92db17dc86f2_1.png"
            },
            "caption": ""
          }
        ]
      }
    ]
  }
}